cbirds/birds.py
cbirds-0.1.0.dist-info/LICENSE
cbirds-0.1.0.dist-info/METADATA
cbirds-0.1.0.dist-info/WHEEL
cbirds-0.1.0.dist-info/top_level.txt
cbirds-0.1.0.dist-info/RECORD
