Metadata-Version: 2.1
Name: cbirds
Version: 0.1.0
Summary: Combinatory Birds
Author-email: João Alvim <joaoafonsoalvim@gmail.com>
Project-URL: repository, https://github.com/jotaalvim/cbirds
Project-URL: Bug Tracker, https://github.com/jotaalvim/cbirds/issues
Keywords: cbirds,combinator,birds,combinator birds,logic
Classifier: License :: OSI Approved :: MIT License
Requires-Python: >=3.7
License-File: LICENSE
Requires-Dist: pointfree
